{
  "hospitals": {
    "은평365든든내과마취통증의학과의원|서울 > 은평구": {
      "seqno": "3617668",
      "hospital": "은평365든든내과마취통증의학과의원",
      "title": "☆5월 중 오픈☆[새절역] 은평365든든내과마취통증의학과 전부서 모집 [5월 중 개원]",
      "region": "서울 > 은평구",
      "sido": "서울",
      "branch": "서부지점",
      "type": "내과",
      "jobs": [
        "임상병리사"
      ],
      "deadline": "2026-07-01",
      "update_date": "2026-04-01",
      "is_closed": false,
      "url": "https://www.medijob.cc/com/cpn/com_cpn_100_view_02?recruitSeqno=3617668",
      "seqnos": [
        "3617668"
      ],
      "count": 1,
      "status": "active",
      "last_seen": "2026-04-20"
    },
    "모두탑365정형외과의원 수지점|경기 > 용인시": {
      "seqno": "3612616",
      "hospital": "모두탑365정형외과의원 수지점",
      "title": "증원*간호과*[주 5일] [26년 3월 9일개원 ]모두탑정형외과 수지점입니다",
      "region": "경기 > 용인시",
      "sido": "경기",
      "branch": "용인지점",
      "type": "정형외과",
      "jobs": [],
      "deadline": "채용시까지",
      "update_date": "2026-04-21",
      "is_closed": false,
      "url": "https://www.medijob.cc/com/cpn/com_cpn_100_view_02?recruitSeqno=3612616",
      "seqnos": [
        "3612616"
      ],
      "count": 1,
      "status": "active",
      "last_seen": "2026-04-21"
    },
    "서울에이스비뇨의학과의원|경기 > 성남시": {
      "seqno": "3611027",
      "hospital": "서울에이스비뇨의학과의원",
      "title": "★6월 1일 개원★ [분당서현역] 서울에이스비뇨의학과 외래팀장/부팀장 & 수술실장 모집",
      "region": "경기 > 성남시",
      "sido": "경기",
      "branch": "성남지점",
      "type": "의원",
      "jobs": [],
      "deadline": "2026-05-07",
      "update_date": "2026-04-08",
      "is_closed": false,
      "url": "https://www.medijob.cc/com/cpn/com_cpn_100_view_02?recruitSeqno=3611027",
      "seqnos": [
        "3611027"
      ],
      "count": 1,
      "status": "active",
      "last_seen": "2026-04-20"
    },
    "가양제일365정형외과의원|서울 > 강서구": {
      "seqno": "3618342",
      "hospital": "가양제일365정형외과의원",
      "title": "[주5일][급여인상▲/신졸기준 270~ /가양역/5월 8일 개원] ●물리치료사 선생님 모십니다 / 가양제일365정형외과",
      "region": "서울 > 강서구",
      "sido": "서울",
      "branch": "일산지점",
      "type": "정형외과",
      "jobs": [
        "간호조무사",
        "임상병리사",
        "물리치료사",
        "방사선사"
      ],
      "deadline": "채용시까지",
      "update_date": "2026-04-18",
      "is_closed": false,
      "url": "https://www.medijob.cc/com/cpn/com_cpn_100_view_02?recruitSeqno=3618342",
      "seqnos": [
        "3618342",
        "3617941",
        "3617127",
        "3617128"
      ],
      "count": 4,
      "status": "active",
      "last_seen": "2026-04-20"
    },
    "의왕탑내과의원|경기 > 의왕시": {
      "seqno": "3618318",
      "hospital": "의왕탑내과의원",
      "title": "11월에 개원한 의왕시 소재 5대암 검진내과에서 간호조무사 선생님을 추가 채용합니다.",
      "region": "경기 > 의왕시",
      "sido": "경기",
      "branch": "안양지점",
      "type": "내과",
      "jobs": [
        "간호조무사"
      ],
      "deadline": "채용시까지",
      "update_date": "2026-04-18",
      "is_closed": false,
      "url": "https://www.medijob.cc/com/cpn/com_cpn_100_view_02?recruitSeqno=3618318",
      "seqnos": [
        "3618318"
      ],
      "count": 1,
      "status": "active",
      "last_seen": "2026-04-19"
    },
    "고트의원|서울 > 서초구": {
      "seqno": "3618293",
      "hospital": "고트의원",
      "title": "[강남역/신규 개원]저희 고트의원과 함께 성장할 개원 멤버를 찾습니다! (피부과, 산부인과)",
      "region": "서울 > 서초구",
      "sido": "서울",
      "branch": "서초지점",
      "type": "의원",
      "jobs": [],
      "deadline": "채용시까지",
      "update_date": "2026-04-21",
      "is_closed": false,
      "url": "https://www.medijob.cc/com/cpn/com_cpn_100_view_02?recruitSeqno=3618293",
      "seqnos": [
        "3618293"
      ],
      "count": 1,
      "status": "active",
      "last_seen": "2026-04-21"
    },
    "서현역본튼튼365의원|경기 > 성남시": {
      "seqno": "3618285",
      "hospital": "서현역본튼튼365의원",
      "title": "★6월개원★ 수인분당선 서현역본튼튼365의원에서 외래간호팀 선생님을 모십니다.",
      "region": "경기 > 성남시",
      "sido": "경기",
      "branch": "성남지점",
      "type": "의원",
      "jobs": [
        "원무"
      ],
      "deadline": "채용시까지",
      "update_date": "2026-04-20",
      "is_closed": false,
      "url": "https://www.medijob.cc/com/cpn/com_cpn_100_view_02?recruitSeqno=3618285",
      "seqnos": [
        "3618285",
        "3618284"
      ],
      "count": 2,
      "status": "active",
      "last_seen": "2026-04-20"
    },
    "서울파스텔치과|서울 > 서초구": {
      "seqno": "3618244",
      "hospital": "서울파스텔치과",
      "title": "★(잠원역 및 반포역 인근,신규개원,면접비지원)★서울파스텔치과 진료실스탭,알바 모집",
      "region": "서울 > 서초구",
      "sido": "서울",
      "branch": "서초지점",
      "type": "치과",
      "jobs": [],
      "deadline": "채용시까지",
      "update_date": "2026-04-21",
      "is_closed": false,
      "url": "https://www.medijob.cc/com/cpn/com_cpn_100_view_02?recruitSeqno=3618244",
      "seqnos": [
        "3618244"
      ],
      "count": 1,
      "status": "active",
      "last_seen": "2026-04-21"
    },
    "험프리스 글로리 정형외과의원|경기 > 평택시": {
      "seqno": "3618195",
      "hospital": "험프리스 글로리 정형외과의원",
      "title": "[5월 중순 개원 예정][급여 및 근무조건 조정][평택 미군부대 인근 1인 정형외과] 방사선사 선생님 모십니다.",
      "region": "경기 > 평택시",
      "sido": "경기",
      "branch": "동탄지점",
      "type": "정형외과",
      "jobs": [
        "방사선사"
      ],
      "deadline": "채용시까지",
      "update_date": "2026-04-18",
      "is_closed": false,
      "url": "https://www.medijob.cc/com/cpn/com_cpn_100_view_02?recruitSeqno=3618195",
      "seqnos": [
        "3618195"
      ],
      "count": 1,
      "status": "active",
      "last_seen": "2026-04-18"
    },
    "주연화내과의원|서울 > 관악구": {
      "seqno": "3614401",
      "hospital": "주연화내과의원",
      "title": "난곡사거리 내과에서 간호조무사 선생님 모십니다 / 신규개원",
      "region": "서울 > 관악구",
      "sido": "서울",
      "branch": "남부2지점",
      "type": "내과",
      "jobs": [
        "간호조무사"
      ],
      "deadline": "채용시까지",
      "update_date": "2026-04-13",
      "is_closed": false,
      "url": "https://www.medijob.cc/com/cpn/com_cpn_100_view_02?recruitSeqno=3614401",
      "seqnos": [
        "3614401"
      ],
      "count": 1,
      "status": "active",
      "last_seen": "2026-04-17"
    },
    "세르테 정형외과의원|서울 > 강남구": {
      "seqno": "3618144",
      "hospital": "세르테 정형외과의원",
      "title": "●[5월 개원예정]● 수술실 PA 모집합니다.(경력)",
      "region": "서울 > 강남구",
      "sido": "서울",
      "branch": "강남지점",
      "type": "정형외과",
      "jobs": [
        "PA"
      ],
      "deadline": "채용시까지",
      "update_date": "2026-04-21",
      "is_closed": false,
      "url": "https://www.medijob.cc/com/cpn/com_cpn_100_view_02?recruitSeqno=3618144",
      "seqnos": [
        "3618144",
        "3618143",
        "3618142"
      ],
      "count": 3,
      "status": "active",
      "last_seen": "2026-04-21"
    },
    "르본정형외과|서울 > 송파구": {
      "seqno": "3616327",
      "hospital": "르본정형외과",
      "title": "[★4월 개원, 잠실역3분거리,주 4.5일제 ]르본정형외과 간호팀 모집★]",
      "region": "서울 > 송파구",
      "sido": "서울",
      "branch": "강동지점",
      "type": "정형외과",
      "jobs": [],
      "deadline": "채용시까지",
      "update_date": "2026-04-21",
      "is_closed": false,
      "url": "https://www.medijob.cc/com/cpn/com_cpn_100_view_02?recruitSeqno=3616327",
      "seqnos": [
        "3616327"
      ],
      "count": 1,
      "status": "active",
      "last_seen": "2026-04-21"
    },
    "오산탑신경외과의원|경기 > 오산시": {
      "seqno": "3616573",
      "hospital": "오산탑신경외과의원",
      "title": "2026년 1월 신규 개원  오산탑신경외과의원 물리치료사 모집",
      "region": "경기 > 오산시",
      "sido": "경기",
      "branch": "동탄지점",
      "type": "신경외과",
      "jobs": [
        "물리치료사"
      ],
      "deadline": "채용시까지",
      "update_date": "2026-04-21",
      "is_closed": false,
      "url": "https://www.medijob.cc/com/cpn/com_cpn_100_view_02?recruitSeqno=3616573",
      "seqnos": [
        "3616573"
      ],
      "count": 1,
      "status": "active",
      "last_seen": "2026-04-21"
    },
    "제물포탑마취통증의학과의원|인천 > 미추홀구": {
      "seqno": "3617978",
      "hospital": "제물포탑마취통증의학과의원",
      "title": "●주5일 근무+월차 지급● 인천 신규개원  / 마취통증의학과 / 간호조무사 선생님 모십니다!(신입선생님 환영)",
      "region": "인천 > 미추홀구",
      "sido": "인천",
      "branch": "-",
      "type": "통증의학과",
      "jobs": [
        "방사선사"
      ],
      "deadline": "채용시까지",
      "update_date": "2026-04-03",
      "is_closed": false,
      "url": "https://www.medijob.cc/com/cpn/com_cpn_100_view_02?recruitSeqno=3617978",
      "seqnos": [
        "3617978"
      ],
      "count": 1,
      "status": "active",
      "last_seen": "2026-04-21"
    },
    "경희예스한의원|서울 > 동대문구": {
      "seqno": "3610499",
      "hospital": "경희예스한의원",
      "title": "서울 외대앞역 개원예정인 경희예스한의원(입원실 4병상) 에서 주간실장(간호사 or 간호조무사자격증필수) 선생님을 모십니다. 교통사고입원실청구가능시 급여+@d",
      "region": "서울 > 동대문구",
      "sido": "서울",
      "branch": "중부지점",
      "type": "한의원",
      "jobs": [
        "간호조무사",
        "간호사"
      ],
      "deadline": "2026-05-06",
      "update_date": "2026-04-07",
      "is_closed": false,
      "url": "https://www.medijob.cc/com/cpn/com_cpn_100_view_02?recruitSeqno=3610499",
      "seqnos": [
        "3610499"
      ],
      "count": 1,
      "status": "active",
      "last_seen": "2026-04-17"
    },
    "365홍제바른정형외과의원|서울 > 서대문구": {
      "seqno": "3616678",
      "hospital": "365홍제바른정형외과의원",
      "title": "(홍제역 주5일+월차1개)신규개원 정형외과입니다. / 간호조무사 선생님 모십니다.",
      "region": "서울 > 서대문구",
      "sido": "서울",
      "branch": "서부지점",
      "type": "정형외과",
      "jobs": [
        "간호조무사",
        "물리치료사"
      ],
      "deadline": "채용시까지",
      "update_date": "2026-04-21",
      "is_closed": false,
      "url": "https://www.medijob.cc/com/cpn/com_cpn_100_view_02?recruitSeqno=3616678",
      "seqnos": [
        "3616678",
        "3616689"
      ],
      "count": 2,
      "status": "active",
      "last_seen": "2026-04-21"
    },
    "고덕삼성본재활의학과의원|서울 > 강동구": {
      "seqno": "3591965",
      "hospital": "고덕삼성본재활의학과의원",
      "title": "★신규개원★주5일근무+연3일 휴가지급[고덕역,강동,하남]원무,접수 구인(정형외과).",
      "region": "서울 > 강동구",
      "sido": "서울",
      "branch": "강동지점",
      "type": "의원",
      "jobs": [
        "원무",
        "접수",
        "임상병리사",
        "간호조무사",
        "방사선사",
        "물리치료사"
      ],
      "deadline": "채용시까지",
      "update_date": "2026-03-10",
      "is_closed": false,
      "url": "https://www.medijob.cc/com/cpn/com_cpn_100_view_02?recruitSeqno=3591965",
      "seqnos": [
        "3591965",
        "3591966",
        "3591968",
        "3591970",
        "3591972",
        "3591974"
      ],
      "count": 6,
      "status": "active",
      "last_seen": "2026-04-20",
      "first_seen": "2026-04-17"
    },
    "아산이웃마취통증의학과|서울 > 송파구": {
      "seqno": "3618637",
      "hospital": "아산이웃마취통증의학과",
      "title": "(5월초 개원예정) 아산이웃마취통의학과에서 함께  할  직원을 모십니다!",
      "region": "서울 > 송파구",
      "sido": "서울",
      "branch": "강동지점",
      "type": "통증의학과",
      "jobs": [],
      "deadline": "2026-04-25",
      "update_date": "2026-04-18",
      "is_closed": false,
      "url": "https://www.medijob.cc/com/cpn/com_cpn_100_view_02?recruitSeqno=3618637",
      "seqnos": [
        "3618637"
      ],
      "count": 1,
      "status": "active",
      "last_seen": "2026-04-20",
      "first_seen": "2026-04-17"
    },
    "성모원탑365신경외과의원|서울 > 강북구": {
      "seqno": "3570451",
      "hospital": "성모원탑365신경외과의원",
      "title": "★신규개원★주5일+*법정연차별도*[삼양사거리역,강북,미아]물리치료사 구인(정형외과)",
      "region": "서울 > 강북구",
      "sido": "서울",
      "branch": "북부지점",
      "type": "신경외과",
      "jobs": [
        "물리치료사"
      ],
      "deadline": "채용시까지",
      "update_date": "2026-02-03",
      "is_closed": false,
      "url": "https://www.medijob.cc/com/cpn/com_cpn_100_view_02?recruitSeqno=3570451",
      "seqnos": [
        "3570451"
      ],
      "count": 1,
      "status": "active",
      "last_seen": "2026-04-21",
      "first_seen": "2026-04-17"
    },
    "똑똑연세내과|서울 > 송파구": {
      "seqno": "3603344",
      "hospital": "똑똑연세내과",
      "title": "[가락동] 신규 개원 검진내과 경력직 간호조무사 선생님 모십니다!",
      "region": "서울 > 송파구",
      "sido": "서울",
      "branch": "강동지점",
      "type": "내과",
      "jobs": [
        "간호조무사"
      ],
      "deadline": "2026-04-27",
      "update_date": "2026-03-28",
      "is_closed": false,
      "url": "https://www.medijob.cc/com/cpn/com_cpn_100_view_02?recruitSeqno=3603344",
      "seqnos": [
        "3603344"
      ],
      "count": 1,
      "status": "active",
      "last_seen": "2026-04-21",
      "first_seen": "2026-04-17"
    },
    "열린숨이비인후과의원|경기 > 남양주시": {
      "seqno": "3618747",
      "hospital": "열린숨이비인후과의원",
      "title": "[별내역] 5월신규개원★ 토요일 or 일요일 아르바이트 간호조무사선생님 구합니다.",
      "region": "경기 > 남양주시",
      "sido": "경기",
      "branch": "남양주지점",
      "type": "의원",
      "jobs": [
        "간호조무사"
      ],
      "deadline": "채용시까지",
      "update_date": "2026-04-18",
      "is_closed": false,
      "url": "https://www.medijob.cc/com/cpn/com_cpn_100_view_02?recruitSeqno=3618747",
      "seqnos": [
        "3618747",
        "3618745"
      ],
      "count": 2,
      "status": "active",
      "last_seen": "2026-04-20",
      "first_seen": "2026-04-18"
    },
    "365성모코끼리튼튼의원|경기 > 의왕시": {
      "seqno": "3618734",
      "hospital": "365성모코끼리튼튼의원",
      "title": "의왕 신규개원) 365성모코끼리튼튼의원 간호조무사 선생님 모십니다.",
      "region": "경기 > 의왕시",
      "sido": "경기",
      "branch": "안양지점",
      "type": "의원",
      "jobs": [
        "물리치료사",
        "원무"
      ],
      "deadline": "",
      "update_date": "2026-03-23",
      "is_closed": false,
      "url": "https://www.medijob.cc/com/cpn/com_cpn_100_view_02?recruitSeqno=3618734",
      "seqnos": [
        "3618734",
        "3618688"
      ],
      "count": 2,
      "status": "active",
      "last_seen": "2026-04-21",
      "first_seen": "2026-04-18"
    },
    "검단탑본정형외과의원|인천 > 서구": {
      "seqno": "3617099",
      "hospital": "검단탑본정형외과의원",
      "title": "★[신규개원/주5일/법정연차/남자기숙사]검단탑본정형외과 물리치료사선생님 구인합니다. ★",
      "region": "인천 > 서구",
      "sido": "인천",
      "branch": "부산1지점",
      "type": "정형외과",
      "jobs": [
        "방사선사",
        "물리치료사"
      ],
      "deadline": "채용시까지",
      "update_date": "2026-04-16",
      "is_closed": false,
      "url": "https://www.medijob.cc/com/cpn/com_cpn_100_view_02?recruitSeqno=3617099",
      "seqnos": [
        "3617099",
        "3617100"
      ],
      "count": 2,
      "status": "active",
      "last_seen": "2026-04-21",
      "first_seen": "2026-04-18"
    },
    "송도통쾌한신경외과의원|인천 > 연수구": {
      "seqno": "3618708",
      "hospital": "송도통쾌한신경외과의원",
      "title": "[26년05월 신규개원]송도통쾌한신경외과의원에서 함께 성장할 물리치료사 팀원을 모십니다",
      "region": "인천 > 연수구",
      "sido": "인천",
      "branch": "인천1지점",
      "type": "신경외과",
      "jobs": [
        "물리치료사"
      ],
      "deadline": "채용시까지",
      "update_date": "2026-04-19",
      "is_closed": false,
      "url": "https://www.medijob.cc/com/cpn/com_cpn_100_view_02?recruitSeqno=3618708",
      "seqnos": [
        "3618708"
      ],
      "count": 1,
      "status": "active",
      "last_seen": "2026-04-20",
      "first_seen": "2026-04-18"
    },
    "계양연세365정형외과의원|인천 > 계양구": {
      "seqno": "3618687",
      "hospital": "계양연세365정형외과의원",
      "title": "★신규개원★주5일+연6일 휴가지급[인천,계양구,계산역,부평,부천]원무,접수,코디 구인(정형외과)",
      "region": "인천 > 계양구",
      "sido": "인천",
      "branch": "인천3지점",
      "type": "정형외과",
      "jobs": [
        "간호조무사",
        "물리치료사",
        "방사선사"
      ],
      "deadline": "2026-07-20",
      "update_date": "2026-04-21",
      "is_closed": false,
      "url": "https://www.medijob.cc/com/cpn/com_cpn_100_view_02?recruitSeqno=3618687",
      "seqnos": [
        "3618687",
        "3618685",
        "3618684"
      ],
      "count": 3,
      "status": "active",
      "last_seen": "2026-04-21",
      "first_seen": "2026-04-18"
    },
    "원본재활의학과|서울 > 강북구": {
      "seqno": "3616733",
      "hospital": "원본재활의학과",
      "title": "★26년5월초개원★ 미아사거리역 신규개원하는 원본재활의학과 (★주 5일) 간호조무사 선생님을 모집합니다.",
      "region": "서울 > 강북구",
      "sido": "서울",
      "branch": "북부지점",
      "type": "기타",
      "jobs": [
        "간호조무사"
      ],
      "deadline": "채용시까지",
      "update_date": "2026-04-16",
      "is_closed": false,
      "url": "https://www.medijob.cc/com/cpn/com_cpn_100_view_02?recruitSeqno=3616733",
      "seqnos": [
        "3616733"
      ],
      "count": 1,
      "status": "active",
      "last_seen": "2026-04-20",
      "first_seen": "2026-04-18"
    },
    "고척튼튼정형외과|서울 > 구로구": {
      "seqno": "3587798",
      "hospital": "고척튼튼정형외과",
      "title": "★5월말 개원예정★ 경력직 350 이상 <고척튼튼정형외과> 방사선사 선생님 모십니다.",
      "region": "서울 > 구로구",
      "sido": "서울",
      "branch": "남부1지점",
      "type": "정형외과",
      "jobs": [
        "방사선사"
      ],
      "deadline": "채용시까지",
      "update_date": "2026-03-04",
      "is_closed": false,
      "url": "https://www.medijob.cc/com/cpn/com_cpn_100_view_02?recruitSeqno=3587798",
      "seqnos": [
        "3587798"
      ],
      "count": 1,
      "status": "active",
      "last_seen": "2026-04-21",
      "first_seen": "2026-04-18"
    },
    "브레인앤슬립의원|서울 > 강남구": {
      "seqno": "3618999",
      "hospital": "브레인앤슬립의원",
      "title": "브레인앤슬립의원 IV 간호사/간호조무사님 모십니다 (6월 중순 개원)",
      "region": "서울 > 강남구",
      "sido": "서울",
      "branch": "강남지점",
      "type": "의원",
      "jobs": [
        "간호조무사",
        "간호사",
        "임상병리사"
      ],
      "deadline": "2026-05-03",
      "update_date": "2026-04-19",
      "is_closed": false,
      "url": "https://www.medijob.cc/com/cpn/com_cpn_100_view_02?recruitSeqno=3618999",
      "seqnos": [
        "3618999",
        "3619002",
        "3619001"
      ],
      "count": 3,
      "status": "active",
      "last_seen": "2026-04-20",
      "first_seen": "2026-04-18"
    },
    "모두튼튼365의원 군산점|전북 > 군산시": {
      "seqno": "3618955",
      "hospital": "모두튼튼365의원 군산점",
      "title": "[주5일][나운동/6월 22일 개원] ●간호과 선생님 모십니다 / 모두튼튼365의원 군산점",
      "region": "전북 > 군산시",
      "sido": "기타",
      "branch": "전주지점",
      "type": "의원",
      "jobs": [
        "임상병리사",
        "방사선사",
        "물리치료사",
        "원무"
      ],
      "deadline": "채용시까지",
      "update_date": "2026-04-19",
      "is_closed": false,
      "url": "https://www.medijob.cc/com/cpn/com_cpn_100_view_02?recruitSeqno=3618955",
      "seqnos": [
        "3618955",
        "3618963",
        "3618958",
        "3618956",
        "3618932",
        "3618926",
        "3618927"
      ],
      "count": 7,
      "status": "active",
      "last_seen": "2026-04-20",
      "first_seen": "2026-04-18"
    },
    "은평마디튼튼365의원|서울 > 은평구": {
      "seqno": "3614146",
      "hospital": "은평마디튼튼365의원",
      "title": "[4월개원예정/은평구]★★은평마디튼튼365의원에서 물리치료사 선생님 구인합니다.★★",
      "region": "서울 > 은평구",
      "sido": "서울",
      "branch": "서부지점",
      "type": "의원",
      "jobs": [],
      "deadline": "채용시까지",
      "update_date": "2026-04-19",
      "is_closed": false,
      "url": "https://www.medijob.cc/com/cpn/com_cpn_100_view_02?recruitSeqno=3614146",
      "seqnos": [
        "3614146"
      ],
      "count": 1,
      "status": "active",
      "last_seen": "2026-04-20",
      "first_seen": "2026-04-18"
    },
    "인덕원바른정형외과의원|경기 > 의왕시": {
      "seqno": "3598694",
      "hospital": "인덕원바른정형외과의원",
      "title": "★신규개원★주6일+연3일 휴가지급[인덕원,안양,범계,평촌,과천]방사선사 팀장님구인(정형외과)",
      "region": "경기 > 의왕시",
      "sido": "경기",
      "branch": "안양지점",
      "type": "정형외과",
      "jobs": [
        "임상병리사",
        "원무",
        "접수",
        "코디",
        "간호조무사",
        "방사선사",
        "물리치료사"
      ],
      "deadline": "채용시까지",
      "update_date": "2026-03-20",
      "is_closed": false,
      "url": "https://www.medijob.cc/com/cpn/com_cpn_100_view_02?recruitSeqno=3598694",
      "seqnos": [
        "3598694",
        "3598723",
        "3598741",
        "3598757",
        "3598763",
        "3598773"
      ],
      "count": 6,
      "status": "active",
      "last_seen": "2026-04-21",
      "first_seen": "2026-04-18"
    },
    "화정바로365정형외과|경기 > 고양시": {
      "seqno": "3606187",
      "hospital": "화정바로365정형외과",
      "title": "[화정역 30초/신규개원/신입환영] 방사선사 선생님 모십니다.",
      "region": "경기 > 고양시",
      "sido": "경기",
      "branch": "일산지점",
      "type": "정형외과",
      "jobs": [
        "방사선사",
        "원무",
        "접수",
        "코디",
        "간호조무사",
        "임상병리사",
        "물리치료사"
      ],
      "deadline": "채용시까지",
      "update_date": "2026-03-31",
      "is_closed": false,
      "url": "https://www.medijob.cc/com/cpn/com_cpn_100_view_02?recruitSeqno=3606187",
      "seqnos": [
        "3606187",
        "3606193",
        "3606202",
        "3606204",
        "3606212"
      ],
      "count": 5,
      "status": "active",
      "last_seen": "2026-04-21",
      "first_seen": "2026-04-18"
    },
    "모두튼튼365의원 일산중산점|경기 > 고양시": {
      "seqno": "3619118",
      "hospital": "모두튼튼365의원 일산중산점",
      "title": "[주 5일][5월 중순 개원]  ●원무과 선생님 모십니다. / 모두튼튼365의원 일산중산점",
      "region": "경기 > 고양시",
      "sido": "경기",
      "branch": "일산지점",
      "type": "의원",
      "jobs": [
        "원무",
        "임상병리사",
        "방사선사",
        "물리치료사"
      ],
      "deadline": "채용시까지",
      "update_date": "2026-04-20",
      "is_closed": false,
      "url": "https://www.medijob.cc/com/cpn/com_cpn_100_view_02?recruitSeqno=3619118",
      "seqnos": [
        "3619118",
        "3617113",
        "3617108",
        "3617107"
      ],
      "count": 4,
      "status": "active",
      "last_seen": "2026-04-20",
      "first_seen": "2026-04-19"
    },
    "압구정정형외과의원|서울 > 강남구": {
      "seqno": "3619198",
      "hospital": "압구정정형외과의원",
      "title": "(압구정역) 신규개원, 압구정정형외과에서 간호조무사 선생님 구인합니다.",
      "region": "서울 > 강남구",
      "sido": "서울",
      "branch": "강남지점",
      "type": "정형외과",
      "jobs": [
        "원무",
        "간호조무사"
      ],
      "deadline": "채용시까지",
      "update_date": "2026-04-20",
      "is_closed": false,
      "url": "https://www.medijob.cc/com/cpn/com_cpn_100_view_02?recruitSeqno=3619198",
      "seqnos": [
        "3619198",
        "3619196"
      ],
      "count": 2,
      "status": "active",
      "last_seen": "2026-04-21",
      "first_seen": "2026-04-20"
    },
    "삼성행신정형외과의원|경기 > 고양시": {
      "seqno": "3599792",
      "hospital": "삼성행신정형외과의원",
      "title": "[4월 신규개원] 삼성행신정형외과에서 방사선사를 모십니다.",
      "region": "경기 > 고양시",
      "sido": "경기",
      "branch": "일산지점",
      "type": "정형외과",
      "jobs": [
        "방사선사"
      ],
      "deadline": "채용시까지",
      "update_date": "2026-03-23",
      "is_closed": false,
      "url": "https://www.medijob.cc/com/cpn/com_cpn_100_view_02?recruitSeqno=3599792",
      "seqnos": [
        "3599792"
      ],
      "count": 1,
      "status": "active",
      "last_seen": "2026-04-21",
      "first_seen": "2026-04-20"
    },
    "마석탑365정형외과의원|경기 > 남양주시": {
      "seqno": "3619919",
      "hospital": "마석탑365정형외과의원",
      "title": "(주5일 or 파트타임가능)남양주 마석역에 위치한 개원예정인 정형외과에서 임상병리사 선생님들을 모십니다.",
      "region": "경기 > 남양주시",
      "sido": "경기",
      "branch": "남양주지점",
      "type": "정형외과",
      "jobs": [
        "임상병리사"
      ],
      "deadline": "채용시까지",
      "update_date": "2026-04-21",
      "is_closed": false,
      "url": "https://www.medijob.cc/com/cpn/com_cpn_100_view_02?recruitSeqno=3619919",
      "seqnos": [
        "3619919"
      ],
      "count": 1,
      "status": "active",
      "last_seen": "2026-04-21",
      "first_seen": "2026-04-20"
    },
    "연세탑튼튼365의원|인천 > 남동구": {
      "seqno": "3611359",
      "hospital": "연세탑튼튼365의원",
      "title": "[주 5일 3월 개원]연세탑튼튼365의원에서 방사선사선생님 모십니다.",
      "region": "인천 > 남동구",
      "sido": "인천",
      "branch": "인천1지점",
      "type": "의원",
      "jobs": [
        "방사선사"
      ],
      "deadline": "채용시까지",
      "update_date": "2026-04-08",
      "is_closed": false,
      "url": "https://www.medijob.cc/com/cpn/com_cpn_100_view_02?recruitSeqno=3611359",
      "seqnos": [
        "3611359"
      ],
      "count": 1,
      "status": "active",
      "last_seen": "2026-04-21",
      "first_seen": "2026-04-20"
    },
    "연세엄지척마취통증의학과의원|서울 > 성동구": {
      "seqno": "3619645",
      "hospital": "연세엄지척마취통증의학과의원",
      "title": "⭐[신금호역/행당역] 연세엄지척마취통증의학과의원 신규개원 코디네이터 선생님 모집합니다!",
      "region": "서울 > 성동구",
      "sido": "서울",
      "branch": "부산1지점",
      "type": "통증의학과",
      "jobs": [
        "코디",
        "물리치료사",
        "간호조무사"
      ],
      "deadline": "2026-05-07",
      "update_date": "2026-04-21",
      "is_closed": false,
      "url": "https://www.medijob.cc/com/cpn/com_cpn_100_view_02?recruitSeqno=3619645",
      "seqnos": [
        "3619645",
        "3619644",
        "3619643"
      ],
      "count": 3,
      "status": "active",
      "last_seen": "2026-04-21",
      "first_seen": "2026-04-20"
    },
    "바로싹통증의학과|서울 > 은평구": {
      "seqno": "3619543",
      "hospital": "바로싹통증의학과",
      "title": "☆26년5월 신규개원☆구파발 바로싹통증의학과에서 신경전도검사 및 원무과업무 가능한 임상병리사 선생님을 초빙합니다.(신규지원가능)",
      "region": "서울 > 은평구",
      "sido": "서울",
      "branch": "서부지점",
      "type": "통증의학과",
      "jobs": [
        "임상병리사",
        "원무",
        "물리치료사",
        "방사선사",
        "간호조무사"
      ],
      "deadline": "채용시까지",
      "update_date": "2026-04-21",
      "is_closed": false,
      "url": "https://www.medijob.cc/com/cpn/com_cpn_100_view_02?recruitSeqno=3619543",
      "seqnos": [
        "3619543",
        "3619537",
        "3619528",
        "3619526",
        "3619523"
      ],
      "count": 5,
      "status": "active",
      "last_seen": "2026-04-21",
      "first_seen": "2026-04-20"
    },
    "태평 최선마취통증의학과|경기 > 성남시": {
      "seqno": "3620161",
      "hospital": "태평 최선마취통증의학과",
      "title": "★26년 6월 초개원★ 태평역 신규개원하는 태평최선마취통증의학과 정형외과 (★주 5일) 간호조무사 선생님을 모집합니다.",
      "region": "경기 > 성남시",
      "sido": "경기",
      "branch": "성남지점",
      "type": "통증의학과",
      "jobs": [
        "간호조무사",
        "방사선사",
        "물리치료사"
      ],
      "deadline": "채용시까지",
      "update_date": "2026-04-21",
      "is_closed": false,
      "url": "https://www.medijob.cc/com/cpn/com_cpn_100_view_02?recruitSeqno=3620161",
      "seqnos": [
        "3620161",
        "3620193",
        "3620190"
      ],
      "count": 3,
      "status": "active",
      "last_seen": "2026-04-21",
      "first_seen": "2026-04-21"
    },
    "서울아산빛정신건강의학과|서울 > 동대문구": {
      "seqno": "3620044",
      "hospital": "서울아산빛정신건강의학과",
      "title": "<1호선 외대앞역 신규 개원 정신건강의학과에서 친절한 간호조무사 선생님 모십니다>",
      "region": "서울 > 동대문구",
      "sido": "서울",
      "branch": "중부지점",
      "type": "기타",
      "jobs": [
        "간호조무사"
      ],
      "deadline": "2026-05-20",
      "update_date": "2026-04-21",
      "is_closed": false,
      "url": "https://www.medijob.cc/com/cpn/com_cpn_100_view_02?recruitSeqno=3620044",
      "seqnos": [
        "3620044"
      ],
      "count": 1,
      "status": "active",
      "last_seen": "2026-04-21",
      "first_seen": "2026-04-21"
    },
    "의료법인 메디피아 메디피움의원|경기 > 화성시": {
      "seqno": "3599115",
      "hospital": "의료법인 메디피아 메디피움의원",
      "title": "의료법인메디피아 메디피움 동탄 재활병원 2026년 12월 개원!  간호부서 책임자 급 공개 채용",
      "region": "경기 > 화성시",
      "sido": "경기",
      "branch": "동탄지점",
      "type": "의원",
      "jobs": [],
      "deadline": "채용시까지",
      "update_date": "2026-03-20",
      "is_closed": false,
      "url": "https://www.medijob.cc/com/cpn/com_cpn_100_view_02?recruitSeqno=3599115",
      "seqnos": [
        "3599115"
      ],
      "count": 1,
      "status": "active",
      "last_seen": "2026-04-21",
      "first_seen": "2026-04-21"
    },
    "동탄365힘찬신경외과|경기 > 화성시": {
      "seqno": "3611179",
      "hospital": "동탄365힘찬신경외과",
      "title": "★26년 4월 신규개원★ 동탄365힘찬신경외과의원 물리치료사 선생님을 초빙합니다!",
      "region": "경기 > 화성시",
      "sido": "경기",
      "branch": "동탄지점",
      "type": "신경외과",
      "jobs": [
        "물리치료사"
      ],
      "deadline": "채용시까지",
      "update_date": "2026-04-08",
      "is_closed": false,
      "url": "https://www.medijob.cc/com/cpn/com_cpn_100_view_02?recruitSeqno=3611179",
      "seqnos": [
        "3611179"
      ],
      "count": 1,
      "status": "active",
      "last_seen": "2026-04-21",
      "first_seen": "2026-04-21"
    },
    "가정역퍼스트정형외과의원|인천 > 서구": {
      "seqno": "3620676",
      "hospital": "가정역퍼스트정형외과의원",
      "title": "(주5일) 6월초에 개원 예정인 가정역퍼스트정형외과에서 책임감 있고 친절한 물리치료사 선생님 구인합니다~!",
      "region": "인천 > 서구",
      "sido": "인천",
      "branch": "부산1지점",
      "type": "정형외과",
      "jobs": [
        "물리치료사"
      ],
      "deadline": "2026-05-21",
      "update_date": "2026-04-21",
      "is_closed": false,
      "url": "https://www.medijob.cc/com/cpn/com_cpn_100_view_02?recruitSeqno=3620676",
      "seqnos": [
        "3620676"
      ],
      "count": 1,
      "status": "active",
      "last_seen": "2026-04-21",
      "first_seen": "2026-04-21"
    },
    "나스정형외과|서울 > 동대문구": {
      "seqno": "3620658",
      "hospital": "나스정형외과",
      "title": "♣ 제기동 6월 중순 개원예정 ♣  주5일+법정연차 별도지급 ♣ 정형외과의원에서 간호조무사 선생님 구인합니다.",
      "region": "서울 > 동대문구",
      "sido": "서울",
      "branch": "중부지점",
      "type": "정형외과",
      "jobs": [
        "간호조무사",
        "원무",
        "방사선사",
        "물리치료사"
      ],
      "deadline": "2026-06-21",
      "update_date": "2026-04-21",
      "is_closed": false,
      "url": "https://www.medijob.cc/com/cpn/com_cpn_100_view_02?recruitSeqno=3620658",
      "seqnos": [
        "3620658",
        "3620659",
        "3620661",
        "3620656"
      ],
      "count": 4,
      "status": "active",
      "last_seen": "2026-04-21",
      "first_seen": "2026-04-21"
    },
    "별내바른365정형외과|경기 > 남양주시": {
      "seqno": "3608005",
      "hospital": "별내바른365정형외과",
      "title": "26년 6월 신규개원★별내바른365정형외과★ 주5일근무 간호조무사 모십니다. [남양주/별내/구리]",
      "region": "경기 > 남양주시",
      "sido": "경기",
      "branch": "남양주지점",
      "type": "정형외과",
      "jobs": [
        "간호조무사",
        "원무",
        "방사선사",
        "물리치료사"
      ],
      "deadline": "채용시까지",
      "update_date": "2026-04-03",
      "is_closed": false,
      "url": "https://www.medijob.cc/com/cpn/com_cpn_100_view_02?recruitSeqno=3608005",
      "seqnos": [
        "3608005",
        "3608015",
        "3608017",
        "3608025"
      ],
      "count": 4,
      "status": "active",
      "last_seen": "2026-04-21",
      "first_seen": "2026-04-21"
    },
    "이수탑정형외과|서울 > 서초구": {
      "seqno": "3620595",
      "hospital": "이수탑정형외과",
      "title": "★[6월 개원/이수역/주5 또는 6일/야간없음] 원무과 선생님 모십니다.",
      "region": "서울 > 서초구",
      "sido": "서울",
      "branch": "서초지점",
      "type": "정형외과",
      "jobs": [
        "원무"
      ],
      "deadline": "채용시까지",
      "update_date": "2026-04-21",
      "is_closed": false,
      "url": "https://www.medijob.cc/com/cpn/com_cpn_100_view_02?recruitSeqno=3620595",
      "seqnos": [
        "3620595"
      ],
      "count": 1,
      "status": "active",
      "last_seen": "2026-04-21",
      "first_seen": "2026-04-21"
    }
  },
  "last_updated": "2026-04-21"
}